secsgem/__init__.py
secsgem/common/__init__.py
secsgem/common/block_send_info.py
secsgem/common/byte_queue.py
secsgem/common/callbacks.py
secsgem/common/codec_jis_x_0201.py
secsgem/common/connection.py
secsgem/common/events.py
secsgem/common/header.py
secsgem/common/helpers.py
secsgem/common/message.py
secsgem/common/protocol.py
secsgem/common/protocol_dispatcher.py
secsgem/common/serial_connection.py
secsgem/common/settings.py
secsgem/common/state_machine.py
secsgem/common/tcp_client_connection.py
secsgem/common/tcp_connection.py
secsgem/common/tcp_server_connection.py
secsgem/common/timeouts.py
secsgem/gem/__init__.py
secsgem/gem/alarm.py
secsgem/gem/alarm_capability.py
secsgem/gem/capability.py
secsgem/gem/clock_capability.py
secsgem/gem/collection_event.py
secsgem/gem/collection_event_capability.py
secsgem/gem/collection_event_link.py
secsgem/gem/collection_event_report.py
secsgem/gem/communication_state_machine.py
secsgem/gem/control_state_machine.py
secsgem/gem/data_value.py
secsgem/gem/data_value_capability.py
secsgem/gem/equipment_constant.py
secsgem/gem/equipment_constants_capability.py
secsgem/gem/equipmenthandler.py
secsgem/gem/handler.py
secsgem/gem/hosthandler.py
secsgem/gem/remote_command.py
secsgem/gem/remote_control_capability.py
secsgem/gem/state_models_capability.py
secsgem/gem/status_data_collection_capability.py
secsgem/gem/status_variable.py
secsgem/hsms/__init__.py
secsgem/hsms/connection_state_machine.py
secsgem/hsms/deselect_req_header.py
secsgem/hsms/deselect_rsp_header.py
secsgem/hsms/header.py
secsgem/hsms/linktest_req_header.py
secsgem/hsms/linktest_rsp_header.py
secsgem/hsms/message.py
secsgem/hsms/protocol.py
secsgem/hsms/reject_req_header.py
secsgem/hsms/select_req_header.py
secsgem/hsms/select_rsp_header.py
secsgem/hsms/separate_req_header.py
secsgem/hsms/settings.py
secsgem/hsms/stream_function_header.py
secsgem/secs/__init__.py
secsgem/secs/data_items/__init__.py
secsgem/secs/data_items/_all.py
secsgem/secs/data_items/abs.py
secsgem-0.3.0.dist-info/LICENSE
secsgem-0.3.0.dist-info/METADATA
secsgem-0.3.0.dist-info/WHEEL
secsgem-0.3.0.dist-info/RECORD
