Metadata-Version: 2.1
Name: secsgem
Version: 0.3.0
Summary: Python SECS/GEM implementation
Home-page: https://github.com/bparzella/secsgem
License: LGPL-2.1-or-later
Keywords: development,hsms,secs,gem
Author: Benjamin Parzella
Author-email: bparzella@gmail.com
Requires-Python: >=3.8,<4.0
Classifier: Development Status :: 3 - Alpha
Classifier: Intended Audience :: Developers
Classifier: License :: OSI Approved
Classifier: License :: OSI Approved :: GNU Lesser General Public License v2 or later (LGPLv2+)
Classifier: Programming Language :: Python :: 3
Classifier: Programming Language :: Python :: 3.8
Classifier: Programming Language :: Python :: 3.9
Classifier: Programming Language :: Python :: 3.10
Classifier: Programming Language :: Python :: 3.11
Classifier: Programming Language :: Python :: 3.12
Classifier: Programming Language :: Python :: 3.7
Classifier: Topic :: Software Development :: Libraries
Requires-Dist: jsonschema (>=4.23.0,<5.0.0)
Requires-Dist: pyserial (>=3.5,<4.0)
Requires-Dist: python-dateutil (>=2.8.1,<3.0.0)
Requires-Dist: pyyaml (>=6.0.1,<7.0.0)
Project-URL: Documentation, https://secsgem.readthedocs.io/
Project-URL: Repository, https://github.com/bparzella/secsgem
